[
    {
        "ID": 11,
        "Template": "微胖姐妹&酷盖男友速抢！立体剪裁秒瘦5斤既视感，冰丝原纱上身自带降温buff，两位数拿下今夏最in防晒战袍，犹豫就会败北！",
        "Template_Class": "品牌营销",
        "Template_Name": "Bh11"
    },
    {
        "ID": 12,
        "Template": "胯宽腿粗的宝子看过来！H型裁剪把肉肉藏得明明白白，会呼吸的面料38°C穿也不粘身，防晒+显瘦+潮搭三合一，这波不下手真的亏！",
        "Template_Class": "品牌营销",
        "Template_Name": "Bh12"
    },
    {
        "ID": 13,
        "Template": "男女同款神仙防晒衣开挂啦！视觉抽脂术拉长全身比例，原纱材质越穿越凉快，99.9元=空调衫+防晒服+出街套装，闺蜜和男友都夸我会买系列",
        "Template_Class": "品牌营销",
        "Template_Name": "Bh13"
    },
    {
        "ID": 14,
        "Template": "救命！这件防晒衣太会藏肉了！微胖穿出纸片人既视感，男生上身秒变清爽少年感，自带清凉感的移动空调衣，现在囤三件还送冰袖！",
        "Template_Class": "品牌营销",
        "Template_Name": "Bh14"
    },
    {
        "ID": 15,
        "Template": "学生党打工人的续命战衣！H版型拯救梨形苹果型身材，透气到像没穿衣服的凉爽，99.9元搞定健身房到约会look，这价格我直接闭眼冲三件！",
        "Template_Class": "品牌营销",
        "Template_Name": "Bh15"
    },
    {
        "ID": 16,
        "Template": "今夏男女通杀的王炸单品！穿上直接PS现实身材，原纱黑科技汗不贴身，防晒指数UPF50+才两位数，刷到就是大数据在救你！",
        "Template_Class": "品牌营销",
        "Template_Name": "Bh16"
    },
    {
        "ID": 17,
        "Template": "微胖界天菜防晒衣实测！视觉减重10斤不开玩笑，百搭白/显瘦黑/元气粉三色可选，透气到能当运动内衣外穿，这性价比不囤货真的睡不着！",
        "Template_Class": "品牌营销",
        "Template_Name": "Bh17"
    },
    {
        "ID": 18,
        "Template": "情侣闺蜜必入的显瘦神器！H型剪裁拯救虎背熊腰，自带凉感的行走小空调，防晒值拉满还不到火锅钱，库存告急手慢无！",
        "Template_Class": "品牌营销",
        "Template_Name": "Bh18"
    },
    {
        "ID": 19,
        "Template": "这件防晒衣让前男友后悔系列！微胖穿出超模直角肩，男生秒变撕漫男身材，原纱面料出汗都不贴肉，现在买还送潮酷防晒面罩！",
        "Template_Class": "品牌营销",
        "Template_Name": "Bh19"
    },
    {
        "ID": 20,
        "Template": "被追着问链接的显瘦玄学！120斤穿出90斤既视感，男生套上直接去拍杂志大片，透气到能当睡衣穿的防晒衣，这个夏天错过真的会哭！",
        "Template_Class": "品牌营销",
        "Template_Name": "Bh20"
    }
]